pdgenere/__init__.py
pdgenere/pdfgene.py
pdgenere-9.1.dist-info/METADATA
pdgenere-9.1.dist-info/WHEEL
pdgenere-9.1.dist-info/top_level.txt
pdgenere-9.1.dist-info/RECORD
