Metadata-Version: 2.1
Name: pdgenere
Version: 9.1
Summary: PDF dynamique
Author: Blemy
Author-email: mathieublemy@01gmail.com
